<?xml version="1.0" encoding="utf-8"?>
<中药 xmlns:xsi="http://www.w3.org/2001/XMLSchema-instance" xsi:noNamespaceSchemaLocation="../zhongyao.cshtml">
	<名称 hz="栀子" py="zhī,zǐ" />
	<介绍>本品为茜草科植物栀子的干燥成熟果实。主产于江西、湖南、湖北、浙江。9 ~ 11月果实成熟呈红黄色时采收，除去果梗及杂质，蒸至上气或置沸水中略烫，取出，干燥。生用或炒焦用。</介绍>
	<药性>
		<气味>苦，寒。</气味>
		<归经>归心、肺、三焦经。</归经>
	</药性>
	<功效>泻火除烦，清热利湿，凉血解毒；外用消肿止痛。</功效>
	<应用>
		<para>
			<title>1.热病心烦</title>
			<text>本品味苦性寒清降，能清泻三焦火邪，泻心火而除烦，为治热病心烦、躁扰不宁之要药，常与<a>淡豆豉</a>同用，如栀子豉汤（《伤寒论》）；治热病火毒炽盛，三焦俱热而见高热烦躁、神昏谵语者，常与<a>黄芩</a>、<a>黄连</a>、<a>黄柏</a>等同用，如黄连解毒汤（《外台秘要》引崔氏方）。</text>
		</para>
		<para>
			<title>2.湿热黄疸</title>
			<text>本品苦能燥湿，寒能清热，善于清利下焦肝胆湿热，治肝胆湿热之黄疸，常与<a>茵陈</a>、<a>大黄</a>等同用，如茵陈蒿汤（《伤寒论》）。</text>
		</para>
		<para>
			<title>3.淋证涩痛</title>
			<text>本品能清下焦湿热，清热凉血，利尿通淋，治血淋、热淋涩痛，常与<a>滑石</a>、<a>车前子</a>、<a>木通</a>等同用，如八正散（《和剂局方》）。</text>
		</para>
		<para>
			<title>4.血热吐衄</title>
			<text>栀子性寒，入血分，能清热凉血以止血，故可用治血热妄行的多种出血。治血热妄行之吐血、衄血者，常与<a>白茅根</a>、<a>大黄</a>、<a>侧柏叶</a>等同用，如十灰散（《十药神书》）；治三焦火盛迫血妄行之吐血、衄血者，常与<a>黄芩</a>、<a>黄连</a>、<a>黄柏</a>等同用，如黄连解毒汤（《外台秘要》引崔氏方）。</text>
		</para>
		<para>
			<title>5.目赤肿痛</title>
			<text>本品能泻火解毒，清肝胆火以明目，治肝胆火热上攻之目赤肿痛，常与<a>大青叶</a>、<a>黄柏</a>等同用，如栀子汤（《外台秘要》）。</text>
		</para>
		<para>
			<title>6.热毒疮疡</title>
			<text>本品能清热泻火，凉血解毒，治热毒疮疡，红肿热痛者，常与<a>金银花</a>、<a>蒲公英</a>、<a>连翘</a>等同用；或与白芷同用，如缩毒散（《普济方》）。</text>
		</para>
		<para>
			<title>7.扭挫伤痛</title>
			<text>本品外用消肿止痛，用治扭挫伤痛，可用生栀子粉与黄酒调成糊状，外敷患处。</text>
		</para>
	</应用>
	<用法用量>煎服，6 ~ 10g。外用生品适量，研末调敷。生栀子走气分而清热泻火，焦栀子入血分而凉血止血。</用法用量>
	<使用注意>本品苦寒伤胃，脾虚便溏者慎用。</使用注意>
</中药>
