<?xml version="1.0" encoding="utf-8"?>
<中药 xmlns:xsi="http://www.w3.org/2001/XMLSchema-instance" xsi:noNamespaceSchemaLocation="../zhongyao.cshtml">
	<名称 hz="珍珠母" py="zhēn,zhū,mǔ" />
	<介绍>本品为蚌科动物三角帆蚌、褶纹冠蚌或珍珠贝科动物马氏珍珠贝的贝壳。主产于江苏、浙江、广东、广西、海南。全年均可捕捞，去肉，洗净，干燥。生用或煅用，用时打碎。</介绍>
	<药性>
		<气味>咸，寒。</气味>
		<归经>归肝、心经。</归经>
	</药性>
	<功效>平肝潜阳，安神定惊，明目退翳。</功效>
	<应用>
		<para>
			<title>1.肝阳上亢，头痛眩晕</title>
			<text>本品咸寒，主入肝经，有与<a>石决明</a>相似的平肝潜阳，清泻肝火作用。治疗肝阳上亢，头痛眩晕者，常与<a>石决明</a>、<a>牡蛎</a>、<a>磁石</a>等平肝潜阳药同用，以增强平抑肝阳作用。若肝阳上亢兼肝热烦躁易怒者，可与<a>钩藤</a>、<a>菊花</a>、<a>夏枯草</a>等清肝火药配伍。若肝阴不足，肝阳上亢所致的头痛眩晕、耳鸣、心悸失眠等症，常与<a>白芍</a>、<a>生地黄</a>、<a>龙齿</a>等同用，如甲乙归藏汤（《医醇賸义》）。</text>
		</para>
		<para>
			<title>2.惊悸失眠</title>
			<text>本品质重入心经，有安神定惊之功。治疗心神不宁，惊悸失眠，可与<a>朱砂</a>、<a>龙骨</a>、<a>琥珀</a>等安神药配伍，如珍珠母丸（《普济本事方》）。治疗癫痫、惊风抽搐，可配伍<a>天麻</a>、<a>钩藤</a>等息风止痉药。</text>
		</para>
		<para>
			<title>3.目赤翳障，视物昏花</title>
			<text>本品性寒，有清肝、明目、退翳之功，用治肝热目赤，羞明，翳障，常与<a>石决明</a>、<a>菊花</a>、<a>车前子</a>等药同用。用治肝虚目暗，视物昏花，则与<a>枸杞子</a>、<a>女贞子</a>、<a>黑芝麻</a>等配伍以养肝明目。治疗夜盲证，可与<a>苍术</a>、猪肝或鸡肝配伍同用。</text>
		</para>
		<para>
			<text>此外，本品研细末外用，能燥湿收敛，用治湿疮瘙痒，溃疡久不收口，口疮等症。用珍珠层粉内服可治胃、十二指肠球部溃疡；制成眼药膏外用，可治疗白内障、角膜炎及结膜炎等。</text>
		</para>
	</应用>
	<用法用量>煎服，10 ~ 25g，先煎。</用法用量>
	<使用注意>本品属性寒镇降之品，故脾胃虚寒及孕妇慎用。</使用注意>
	<鉴别用药>
		<鉴药>石决明</鉴药>
		<鉴药>珍珠母</鉴药>
		石决明与珍珠母皆为贝壳类中药，均为咸寒之品，入肝经，均能平肝潜阳，清肝明目，用治肝阳上亢、肝经有热之头痛眩晕、耳鸣及肝热目疾，目昏翳障。但石决明为凉肝、镇肝之要药，兼能益肝阴，善治肝肾阴虚，眩晕、耳鸣等阳亢之证；又长于清肝明目，故目赤肿痛、翳膜遮睛、视物昏花等症，不论虚实，皆可应用，为眼科要药。珍珠母又入心经，能安神定惊，故心神不宁，惊悸失眠，烦躁等多用。
	</鉴别用药>
</中药>
